short_urls/__init__.py
short_urls/config.py
short_urls/short_urls.py
short_urls_client-1.0.0.data/scripts/short-urls
short_urls_client-1.0.0.dist-info/METADATA
short_urls_client-1.0.0.dist-info/WHEEL
short_urls_client-1.0.0.dist-info/top_level.txt
short_urls_client-1.0.0.dist-info/RECORD
