Metadata-Version: 2.1
Name: short-urls-client
Version: 1.0.0
Summary: A python client for the https://github.com/jamesridgway/aws-lambda-short-url project.
Home-page: https://github.com/jamesridgway/short-urls-client
Author: James Ridgway
Author-email: UNKNOWN
License: MIT
Platform: UNKNOWN
Requires-Dist: pyperclip
Requires-Dist: requests
